Metadata-Version: 2.1
Name: byozdemir-sendmessage
Version: 0.0.2
Summary: It's helps you tou send message via populer apps
Author: Byozdemir
Author-email: emrenetwork@yandex.com
License: MIT
Keywords: telegram messager,discord messager
